{
  "$schema": "https://developer.microsoft.com/json-schemas/spfx-build/package-solution.schema.json",
  "solution": {
    "name": "clarity-client-side-solution",
    "id": "3bdc9333-07a6-4aef-93bd-20032da0061c",
    "version": "1.0.0.0",
    "includeClientSideAssets": true,
    "skipFeatureDeployment": true,
    "isDomainIsolated": false,
    "metadata": {
      "shortDescription": {
        "default": "clarity description"
      },
      "longDescription": {
        "default": "clarity description"
      },
      "screenshotPaths": [],
      "videoUrl": "",
      "categories": []
    },
    "developer": {
      "name": "",
      "websiteUrl": "",
      "privacyUrl": "",
      "termsOfUseUrl": "",
      "mpnId": ""
    },
    "features": [
      {
        "title": "Application Extension - Deployment of custom action.",
        "description": "Deploys a custom action with ClientSideComponentId association",
        "id": "25ba4862-5bfa-4ca2-ac65-382dc9b0f5af",
        "version": "1.0.0.0",
        "assets": {
          "elementManifests": [
            "elements.xml",
            "ClientSideInstance.xml"
          ]
        }
      }
    ]
  },
  "paths": {
    "zippedPackage": "solution/clarity.sppkg"
  }
}
