{
  "$schema": "https://developer.microsoft.com/json-schemas/spfx-build/package-solution.schema.json",
  "solution": {
    "name": "react-application-news-ticker-client-side-solution",
    "id": "b5d9ad1f-5198-4647-a5b6-5dbc17bf1608",
    "version": "1.0.0.0",
    "includeClientSideAssets": true,
    "skipFeatureDeployment": true,
    "isDomainIsolated": false,
    "developer": {
      "name": "",
      "websiteUrl": "",
      "privacyUrl": "",
      "termsOfUseUrl": "",
      "mpnId": "Undefined-1.14.0"
    },
    "metadata": {
      "shortDescription": {
        "default": "react-application-news-ticker description"
      },
      "longDescription": {
        "default": "react-application-news-ticker description"
      },
      "screenshotPaths": [],
      "videoUrl": "",
      "categories": []
    },
    "features": [
      {
        "title": "Application Extension - Deployment of custom action",
        "description": "Deploys a custom action with ClientSideComponentId association",
        "id": "73d57e47-1fd2-4f03-81d9-b2ecccd76c51",
        "version": "1.0.0.0",
        "assets": {
          "elementManifests": [
            "elements.xml",
            "ClientSideInstance.xml"
          ]
        }
      }
    ]
  },
  "paths": {
    "zippedPackage": "solution/react-application-news-ticker.sppkg"
  }
}
