{
  "$schema": "https://developer.microsoft.com/json-schemas/spfx-build/package-solution.schema.json",
  "solution": {
    "name": "O365C- CommandSet Authenticated Flow Trigger",
    "id": "1211df76-6adc-4956-82fd-bd6483da8787",
    "version": "1.0.0.2",
    "includeClientSideAssets": true,
    "skipFeatureDeployment": false,
    "isDomainIsolated": false,
    "webApiPermissionRequests": [
      {
        "resource": "Microsoft Flow Service",        
        "scope": "user_impersonation"
      }
    ],
    "developer": {
      "name": "",
      "websiteUrl": "",
      "privacyUrl": "",
      "termsOfUseUrl": "",
      "mpnId": "Undefined-1.22.0"
    },
    "metadata": {
      "shortDescription": {
        "default": "O36C- CommandSet Authenticated Flow Trigger description"
      },
      "longDescription": {
        "default": "O36C- CommandSet Authenticated Flow Trigger description"
      },
      "screenshotPaths": [],
      "videoUrl": "",
      "categories": []
    },
    "features": [
      {
        "title": "Application Extension - Deployment of custom action",
        "description": "Deploys a custom action with ClientSideComponentId association",
        "id": "b09c1563-7e71-45a4-8773-26953f9f004c",
        "version": "1.0.0.0",
        "assets": {
          "elementManifests": [
            "elements.xml",
            "ClientSideInstance.xml"
          ]
        }
      }
    ]
  },
  "paths": {
    "zippedPackage": "solution/o365c-commandset-authenticated-flow-trigger.sppkg"
  }
}
